Workbook

Sheet Company Overview
A1: COMPANY OVERVIEW - INFOSYS LIMITTED
A2: PARTICULARS | B2: DETAILS
A3: Company Name | B3: Infosys limitted
A4: Industry | B4: Information Technology Services
A5: Headquarters | B5: Bengaluru, Karnataka, India
A6: Founded | B6: 1981
A7: Founders | B7: N.R. Narayana Murthy and six co-founders
A8: CEO | B8: Salil Parekh
A9: Employees | B9: 323,000+
A10: Stock Exchange | B10: NSE & BSE
A11: Business Segments | B11: Digital Services, Consulting, Cloud, AI, Engineering Services, Business Process
A14: OBJECTIVE
A15: To analyze the financial performance of Infosys ltd using its annual report by evaluating revenue, profitability, financial position, cash flows, and key financial ratios over three financial years.
A19: COMPANY DESCRIPTION
A20: Infosys ltd is a global information technology & counsulting company headquartered in Bengaluru, India. It provides digital transformation, cloud, artificial intelligence, engineering, and business consulting services to clients across various industries worldwide.
A25: WHY I SELECTED THIS COMPANY
A26: > Leading Indian IT company with global operations > Transparent and comprehensive annual reports. > Suitable for financial statement and ratio analysis.
A30: TOOLS USED
A31: > Microsoft Excel 2021 > Infosys Annual Report FY 2025 > Financial Statement Analysis > Ratio Analysis

Sheet Income Statement
A1: INCOME STATEMENT
B2: unit: ₹ crore
A3: Particulars | B3: FY 2025 | C3: FY 2024 | D3: FY 2023
A4: Revenue | B4: 162990 | C4: 153670 | D4: 146767
A5: Profit Before Tax | B5: 37608 | C5: 35988 | D5: 33322
A6: Net Profit | B6: 26750 | C6: 26248 | D6: 24108

Sheet Balance Sheet
A1: BALANCE SHEET
B2: unit: ₹ crore
A3: Particulars | B3: FY 2025 | C3: FY 2024 | D3: FY 2023
A4: Total Assets | B4: 148903 | C4: 137814 | D4: 125816
A5: Total Liabilities | B5: 42850 | C5: 38794 | D5: 39186
A6: Total Equity | B6: 96203 | C6: 88461 | D6: 75795

Sheet Cash Flow
A1: CASH FLOW
B2: unit: ₹ crore
A3: Particulars | B3: FY 2025 | C3: FY 2024 | D3: FY 2023
A4: Operating Activities | B4: 35694 | C4: 25210 | D4: 22467
A5: Investing Activities | B5: -1946 | C5: -5009 | D5: -1209
A6: Financing Activities | B6: -24161 | C6: -17504 | D6: -26695

Sheet Ratio Analysis
A1: RATIO ANALYSIS
A3: Ratio | B3: FY 2025 | C3: FY 2024 | D3: FY 2023
A4: Net Profit Margin | B4: ='Income Statement'!B6/'Income Statement'!B4 -> 0.1641205 | C4: ='Income Statement'!C6/'Income Statement'!C4 -> 0.17080757 | D4: ='Income Statement'!D6/'Income Statement'!D4 -> 0.16426036
A5: Return on Equity (ROE) | B5: ='Income Statement'!B6/'Balance Sheet'!B6 -> 0.27805786 | C5: ='Income Statement'!C6/'Balance Sheet'!C6 -> 0.29671833 | D5: ='Income Statement'!D6/'Balance Sheet'!D6 -> 0.31806847
A6: Return on Assets (ROA) | B6: ='Income Statement'!B6/'Balance Sheet'!B4 -> 0.17964715 | C6: ='Income Statement'!C6/'Balance Sheet'!C4 -> 0.1904596 | D6: ='Income Statement'!D6/'Balance Sheet'!D4 -> 0.19161315
A7: Debt-to-Equity Ratio | B7: ='Balance Sheet'!B5/'Balance Sheet'!B6 -> 0.44541231 | C7: ='Balance Sheet'!C5/'Balance Sheet'!C6 -> 0.43854354 | D7: ='Balance Sheet'!D5/'Balance Sheet'!D6 -> 0.5169998

Sheet Dashboard
A1: INFOSYS LIMITTED - FINANCIAL PERFORMANCE DASHBOARD
A2: (FY 2025 | All Financial values are in ₹ crore)
O8: Revenue | S8: Net profit
N9: FY 2023 | O9: ='Income Statement'!D4 -> 146767 | R9: FY 2023 | S9: ='Income Statement'!D6 -> 24108
N10: FY 2024 | O10: ='Income Statement'!C4 -> 153670 | R10: FY 2024 | S10: ='Income Statement'!C6 -> 26248
N11: FY 2025 | O11: ='Income Statement'!B4 -> 162990 | R11: FY 2025 | S11: ='Income Statement'!B6 -> 26750
N18: Asset | O18: Liability | R18: Operating | S18: Investing | T18: Financing
M19: FY 2023 | N19: ='Balance Sheet'!D4 -> 125816 | O19: ='Balance Sheet'!D5 -> 39186 | Q19: FY 2023 | R19: ='Cash Flow'!D4 -> 22467 | S19: ='Cash Flow'!D5 -> -1209 | T19: ='Cash Flow'!D6 -> -26695
M20: FY 2024 | N20: ='Balance Sheet'!C4 -> 137814 | O20: ='Balance Sheet'!C5 -> 38794 | Q20: FY 2024 | R20: ='Cash Flow'!C4 -> 25210 | S20: ='Cash Flow'!C5 -> -5009 | T20: ='Cash Flow'!C6 -> -17504
M21: FY 2025 | N21: ='Balance Sheet'!B4 -> 148903 | O21: ='Balance Sheet'!B5 -> 42850 | Q21: FY 2025 | R21: ='Cash Flow'!B4 -> 35694 | S21: ='Cash Flow'!B5 -> -1946 | T21: ='Cash Flow'!B6 -> -24161
N32: FY 2023 | O32: FY 2024 | P32: FY 2025 | S32: Revenue | T32: Net profit
M33: Net profit | N33: ='Ratio Analysis'!D4 -> 0.16426036 | O33: ='Ratio Analysis'!C4 -> 0.17080757 | P33: ='Ratio Analysis'!B4 -> 0.1641205 | R33: FY 2023 | S33: ='Income Statement'!D4 -> 146767 | T33: ='Income Statement'!D6 -> 24108
M34: ROE | N34: ='Ratio Analysis'!D5 -> 0.31806847 | O34: ='Ratio Analysis'!C5 -> 0.29671833 | P34: ='Ratio Analysis'!B5 -> 0.27805786 | R34: FY 2024 | S34: ='Income Statement'!C4 -> 153670 | T34: ='Income Statement'!C6 -> 26248
M35: ROA | N35: ='Ratio Analysis'!D6 -> 0.19161315 | O35: ='Ratio Analysis'!C6 -> 0.1904596 | P35: ='Ratio Analysis'!B6 -> 0.17964715 | R35: FY 2025 | S35: ='Income Statement'!B4 -> 162990 | T35: ='Income Statement'!B6 -> 26750
A46: Source: Infosys Annual Reports (FY2023–FY2025) | Dashboard created using Microsoft Excel 2021
